bppy/__init__.py
bppy/analysis/__init__.py
bppy/analysis/bprogram_converter.py
bppy/analysis/dfs_bprogram_verifier.py
bppy/analysis/symbolic_bprogram_verifier.py
bppy/execution/__init__.py
bppy/execution/listeners/__init__.py
bppy/execution/listeners/b_program_runner_listener.py
bppy/execution/listeners/print_b_program_runner_listener.py
bppy/gym/__init__.py
bppy/gym/bp_action_space.py
bppy/gym/bp_env.py
bppy/gym/bp_observation_space.py
bppy/gym/simple_bp_observation_space.py
bppy/model/__init__.py
bppy/model/b_event.py
bppy/model/b_thread.py
bppy/model/bprogram.py
bppy/model/event_set.py
bppy/model/sync_statement.py
bppy/model/event_selection/__init__.py
bppy/model/event_selection/event_selection_strategy.py
bppy/model/event_selection/experimental_smt_event_selection_strategy.py
bppy/model/event_selection/priority_based_event_selection_strategy.py
bppy/model/event_selection/rich_event_selection_strategy.py
bppy/model/event_selection/simple_event_selection_strategy.py
bppy/model/event_selection/smt_event_selection_strategy.py
bppy/model/event_selection/solver_based_event_selection_strategy.py
bppy/utils/__init__.py
bppy/utils/dfs.py
bppy/utils/exceptions.py
bppy/utils/weighted_sampling.py
bppy/utils/z3helper.py
bppy-1.0.3.dist-info/licenses/LICENSE
bppy-1.0.3.dist-info/METADATA
bppy-1.0.3.dist-info/WHEEL
bppy-1.0.3.dist-info/top_level.txt
bppy-1.0.3.dist-info/RECORD
