Metadata-Version: 2.4
Name: bppy
Version: 1.0.3
Summary: BPpy: Behavioral Programming In Python
Home-page: https://github.com/bThink-BGU/BPpy
Author: Tom Yaacov
Author-email: tomyaacov1210@gmail.com
Classifier: Programming Language :: Python :: 3
Classifier: License :: OSI Approved :: MIT License
Classifier: Operating System :: OS Independent
Requires-Python: >=3.9
License-File: LICENSE
Requires-Dist: z3-solver>=4.8.5.0
Provides-Extra: gym
Requires-Dist: gymnasium>=0.28.1; extra == "gym"
Requires-Dist: stable-baselines3>=2.0.0; extra == "gym"
Provides-Extra: develop
Requires-Dist: gymnasium>=0.28.1; extra == "develop"
Requires-Dist: stable-baselines3>=2.0.0; extra == "develop"
Requires-Dist: Sphinx>=5.3.0; extra == "develop"
Requires-Dist: sphinx-rtd-theme>=1.2.1; extra == "develop"
Requires-Dist: graphviz>=0.20.1; extra == "develop"
Requires-Dist: pygame>=2.1.2; extra == "develop"
Dynamic: author
Dynamic: author-email
Dynamic: classifier
Dynamic: description
Dynamic: description-content-type
Dynamic: home-page
Dynamic: license-file
Dynamic: provides-extra
Dynamic: requires-dist
Dynamic: requires-python
Dynamic: summary
